{"cameraMode":{"drawMode":0,"name":"Shaded","section":"Shading Mode"},"sceneLighting":true,"audioPlay":false,"sceneViewState":{"m_AlwaysRefresh":false,"showFog":true,"showSkybox":true,"showFlares":true,"showImageEffects":true,"showParticleSystems":true,"showVisualEffectGraphs":true,"m_FxEnabled":true},"in2DMode":false,"pivot":{"x":23.773624420166017,"y":-4.891026496887207,"z":7.4210004806518559},"rotation":{"x":-0.1687593162059784,"y":-0.1112169623374939,"z":0.01979605108499527,"w":-0.9793535470962524},"size":12.179986000061036,"orthographic":false}